mm_agent_mcp/__init__.py
mm_agent_mcp/server.py
mm_agent_mcp-0.1.4.dist-info/METADATA
mm_agent_mcp-0.1.4.dist-info/WHEEL
mm_agent_mcp-0.1.4.dist-info/entry_points.txt
mm_agent_mcp-0.1.4.dist-info/top_level.txt
mm_agent_mcp-0.1.4.dist-info/RECORD
