Metadata-Version: 2.4
Name: mm-agent-mcp
Version: 0.1.4
Summary: Add your description here
Requires-Python: >=3.12
Requires-Dist: aiohttp>=3.12.0
Requires-Dist: mcp>=1.9.1
Requires-Dist: requests>=2.32.3
